sanloop/__init__.py
sanloop/sanloop.py
sanloop-0.1.dist-info/LICENSE
sanloop-0.1.dist-info/METADATA
sanloop-0.1.dist-info/WHEEL
sanloop-0.1.dist-info/top_level.txt
sanloop-0.1.dist-info/RECORD
